Metadata-Version: 2.1
Name: odoo-addon-sale_report_delivered_subtotal
Version: 18.0.1.0.0.2
Requires-Python: >=3.10
Requires-Dist: odoo==18.0.*
Summary: Sale Report Delivered subtotal
Home-page: https://github.com/OCA/sale-reporting
License: AGPL-3
Author: Tecnativa,Odoo Community Association (OCA)
Author-email: support@odoo-community.org
Classifier: Programming Language :: Python
Classifier: Framework :: Odoo
Classifier: Framework :: Odoo :: 18.0
Classifier: License :: OSI Approved :: GNU Affero General Public License v3
Classifier: Development Status :: 5 - Production/Stable
